binary coded decimal counter/bcd_counter.vhd
library ieee;
use ieee.std_logic_1164.all;
entity D_flipflop is
    port (
        clk : in std_logic;
        rst : in std_logic;
        d   : in std_logic;
        q   : out std_logic
    );
end D_flipflop;
architecture flip of D_flipflop is

    signal tmp:std_logic;

begin
    process(clk)
    begin
        if rising_edge(clk) then
            if rst = '1' then
                tmp <= '0';
                
            else
                tmp <= d;
                
            end if;
        end if;
    end process;
q <= tmp;
end architecture;
-------------------------------------------------
library ieee;
use ieee.std_logic_1164.all;

entity bcd_counter is
    port (
        clk : in std_logic;
        rst : in std_logic;
        x   : in std_logic;
        z   : out std_logic_vector(3 downto 0)
    );
end bcd_counter;

architecture count of bcd_counter is
    component D_flipflop is
        port (
            clk : in std_logic;
            rst : in std_logic;
            d   : in std_logic;
            q   : out std_logic
        );
    end component;
    signal q1,q2,q3,q4: std_logic;
    signal xb,q1b,q2b,q3b,q4b: std_logic;
    signal d1,d2,d3,d4: std_logic;

begin
    xb <= not x;
    q1b <= not q1;
    q2b <= not q2;
    q3b <= not q3;
    q4b <= not q4;
    d1 <= (xb and q1 and q4b)or(x and q1 and q4)or(xb and q2 and q3 and q4)or(x and q1b and q2b and q3b and q4b);
    d2 <= (xb and q2 and q3b)or(q2 and q3 and q4b)or(x and q2 and q4)or(x and q1 and q4b)or(xb and q2b and q3 and q4);
    d3 <= (xb and q3 and q4b)or(x and q3 and q4)or(x and q1 and q4b)or(xb and q1b and q3b and q4)or(x and q2 and q3b and q4b);
    d4 <= q4b;
    f_1: D_flipflop port map(clk,rst,d1,q1);
    f_2: D_flipflop port map(clk,rst,d2,q2);
    f_3: D_flipflop port map(clk,rst,d3,q3);
    f_4: D_flipflop port map(clk,rst,d4,q4);
    z(3) <= q1;
    z(2) <= q2;
    z(1) <= q3;
    z(0) <= q4;

end architecture;

binary coded decimal counter/tb_bcd_counter.vhd
library ieee;
use ieee.std_logic_1164.all;

entity tb_bcd_counter is
end tb_bcd_counter;

architecture tb of tb_bcd_counter is

    component bcd_counter
        port (clk : in std_logic;
              rst : in std_logic;
              x   : in std_logic;
              z   : out std_logic_vector (3 downto 0));
    end component;

    signal clk : std_logic;
    signal rst : std_logic;
    signal x   : std_logic;
    signal z   : std_logic_vector (3 downto 0);

    constant TbPeriod : time := 1000 ns; 
    signal TbClock : std_logic := '0';
    signal TbSimEnded : std_logic := '0';

begin

    dut : bcd_counter
    port map (clk => clk,
              rst => rst,
              x   => x,
              z   => z);

    -- Clock generation
    TbClock <= not TbClock after TbPeriod/2 when TbSimEnded /= '1' else '0';

    clk <= TbClock;

    stimuli : process
    begin
        x <= '0';

        -- Reset generation
        rst <= '1';
        wait for TbPeriod;
        rst <= '0';
        wait for TbPeriod;

        x <='0';
        wait for 100 * TbPeriod;
        x <='1';
        wait for 100 * TbPeriod;
        -- Stop the clock and hence terminate the simulation
        TbSimEnded <= '1';
        wait;
    end process;

end tb;

binary coded decimal counter/counter.vcd
$date
  Thu Apr 28 12:57:15 2022
$end
$version
  GHDL v0
$end
$timescale
  1 fs
$end
$scope module standard $end
$upscope $end
$scope module std_logic_1164 $end
$upscope $end
$scope module tb_bcd_counter $end
$var reg 1 ! clk $end
$var reg 1 " rst $end
$var reg 1 # x $end
$var reg 4 $ z[3:0] $end
$var reg 1 % tbclock $end
$var reg 1 & tbsimended $end
$scope module dut $end
$var reg 1 ' clk $end
$var reg 1 ( rst $end
$var reg 1 ) x $end
$var reg 4 * z[3:0] $end
$var reg 1 + q1 $end
$var reg 1 , q2 $end
$var reg 1 - q3 $end
$var reg 1 . q4 $end
$var reg 1 / xb $end
$var reg 1 0 q1b $end
$var reg 1 1 q2b $end
$var reg 1 2 q3b $end
$var reg 1 3 q4b $end
$var reg 1 4 d1 $end
$var reg 1 5 d2 $end
$var reg 1 6 d3 $end
$var reg 1 7 d4 $end
$scope module f_1 $end
$var reg 1 8 clk $end
$var reg 1 9 rst $end
$var reg 1 : d $end
$var reg 1 ; q $end
$var reg 1 < tmp $end
$upscope $end
$scope module f_2 $end
$var reg 1 = clk $end
$var reg 1 > rst $end
$var reg 1 ? d $end
$var reg 1 @ q $end
$var reg 1 A tmp $end
$upscope $end
$scope module f_3 $end
$var reg 1 B clk $end
$var reg 1 C rst $end
$var reg 1 D d $end
$var reg 1 E q $end
$var reg 1 F tmp $end
$upscope $end
$scope module f_4 $end
$var reg 1 G clk $end
$var reg 1 H rst $end
$var reg 1 I d $end
$var reg 1 J q $end
$var reg 1 K tmp $end
$upscope $end
$upscope $end
$upscope $end
$enddefinitions $end
#0
0!
1"
0#
bUUUU $
0%
0&
0'
1(
0)
bUUUU *
U+
U,
U-
U.
1/
U0
U1
U2
U3
U4
U5
U6
U7
08
19
U:
U;
U<
0=
1>
U?
U@
UA
0B
1C
UD
UE
UF
0G
1H
UI
UJ
UK
#500000000
1!
b0000 $
1%
1'
b0000 *
0+
0,
0-
0.
10
11
12
13
04
05
06
17
18
0:
0;
0<
1=
0?
0@
0A
1B
0D
0E
0F
1G
1I
0J
0K
#1000000000
0!
0"
0%
0'
0(
08
09
0=
0>
0B
0C
0G
0H
#1500000000
1!
b0001 $
1%
1'
b0001 *
1.
03
16
07
18
1=
1B
1D
1G
0I
1J
1K
#2000000000
0!
0%
0'
08
0=
0B
0G
#2500000000
1!
b0010 $
1%
1'
b0010 *
1-
0.
02
13
16
17
18
1=
1B
1D
1E
1F
1G
1I
0J
0K
#3000000000
0!
0%
0'
08
0=
0B
0G
#3500000000
1!
b0011 $
1%
1'
b0011 *
1.
03
15
06
07
18
1=
1?
1B
0D
1G
0I
1J
1K
#4000000000
0!
0%
0'
08
0=
0B
0G
#4500000000
1!
b0100 $
1%
1'
b0100 *
1,
0-
0.
01
12
13
15
17
18
1=
1?
1@
1A
1B
0E
0F
1G
1I
0J
0K
#5000000000
0!
0%
0'
08
0=
0B
0G
#5500000000
1!
b0101 $
1%
1'
b0101 *
1.
03
16
07
18
1=
1B
1D
1G
0I
1J
1K
#6000000000
0!
0%
0'
08
0=
0B
0G
#6500000000
1!
b0110 $
1%
1'
b0110 *
1-
0.
02
13
16
17
18
1=
1B
1D
1E
1F
1G
1I
0J
0K
#7000000000
0!
0%
0'
08
0=
0B
0G
#7500000000
1!
b0111 $
1%
1'
b0111 *
1.
03
14
05
06
07
18
1:
1=
0?
1B
0D
1G
0I
1J
1K
#8000000000
0!
0%
0'
08
0=
0B
0G
#8500000000
1!
b1000 $
1%
1'
b1000 *
1+
0,
0-
0.
00
11
12
13
14
17
18
1:
1;
1<
1=
0@
0A
1B
0E
0F
1G
1I
0J
0K
#9000000000
0!
0%
0'
08
0=
0B
0G
#9500000000
1!
b1001 $
1%
1'
b1001 *
1.
03
04
07
18
0:
1=
1B
1G
0I
1J
1K
#10000000000
0!
0%
0'
08
0=
0B
0G
#10500000000
1!
b0000 $
1%
1'
b0000 *
0+
0.
10
13
17
18
0;
0<
1=
1B
1G
1I
0J
0K
#11000000000
0!
0%
0'
08
0=
0B
0G
#11500000000
1!
b0001 $
1%
1'
b0001 *
1.
03
16
07
18
1=
1B
1D
1G
0I
1J
1K
#12000000000
0!
0%
0'
08
0=
0B
0G
#12500000000
1!
b0010 $
1%
1'
b0010 *
1-
0.
02
13
16
17
18
1=
1B
1D
1E
1F
1G
1I
0J
0K
#13000000000
0!
0%
0'
08
0=
0B
0G
#13500000000
1!
b0011 $
1%
1'
b0011 *
1.
03
15
06
07
18
1=
1?
1B
0D
1G
0I
1J
1K
#14000000000
0!
0%
0'
08
0=
0B
0G
#14500000000
1!
b0100 $
1%
1'
b0100 *
1,
0-
0.
01
12
13
15
17
18
1=
1?
1@
1A
1B
0E
0F
1G
1I
0J
0K
#15000000000
0!
0%
0'
08
0=
0B
0G
#15500000000
1!
b0101 $
1%
1'
b0101 *
1.
03
16
07
18
1=
1B
1D
1G
0I
1J
1K
#16000000000
0!
0%
0'
08
0=
0B
0G
#16500000000
1!
b0110 $
1%
1'
b0110 *
1-
0.
02
13
16
17
18
1=
1B
1D
1E
1F
1G
1I
0J
0K
#17000000000
0!
0%
0'
08
0=
0B
0G
#17500000000
1!
b0111 $
1%
1'
b0111 *
1.
03
14
05
06
07
18
1:
1=
0?
1B
0D
1G
0I
1J
1K
#18000000000
0!
0%
0'
08
0=
0B
0G
#18500000000
1!
b1000 $
1%
1'
b1000 *
1+
0,
0-
0.
00
11
12
13
14
17
18
1:
1;
1<
1=
0@
0A
1B
0E
0F
1G
1I
0J
0K
#19000000000
0!
0%
0'
08
0=
0B
0G
#19500000000
1!
b1001 $
1%
1'
b1001 *
1.
03
04
07
18
0:
1=
1B
1G
0I
1J
1K
#20000000000
0!
0%
0'
08
0=
0B
0G
#20500000000
1!
b0000 $
1%
1'
b0000 *
0+
0.
10
13
17
18
0;
0<
1=
1B
1G
1I
0J
0K
#21000000000
0!
0%
0'
08
0=
0B
0G
#21500000000
1!
b0001 $
1%
1'
b0001 *
1.
03
16
07
18
1=
1B
1D
1G
0I
1J
1K
#22000000000
0!
0%
0'
08
0=
0B
0G
#22500000000
1!
b0010 $
1%
1'
b0010 *
1-
0.
02
13
16
17
18
1=
1B
1D
1E
1F
1G
1I
0J
0K
#23000000000
0!
0%
0'
08
0=
0B
0G
#23500000000
1!
b0011 $
1%
1'
b0011 *
1.
03
15
06
07
18
1=
1?
1B
0D
1G
0I
1J
1K
#24000000000
0!
0%
0'
08
0=
0B
0G
#24500000000
1!
b0100 $
1%
1'
b0100 *
1,
0-
0.
01
12
13
15
17
18
1=
1?
1@
1A
1B
0E
0F
1G
1I
0J
0K
#25000000000
0!
0%
0'
08
0=
0B
0G
#25500000000
1!
b0101 $
1%
1'
b0101 *
1.
03
16
07
18
1=
1B
1D
1G
0I
1J
1K
#26000000000
0!
0%
0'
08
0=
0B
0G
#26500000000
1!
b0110 $
1%
1'
b0110 *
1-
0.
02
13
16
17
18
1=
1B
1D
1E
1F
1G
1I
0J
0K
#27000000000
0!
0%
0'
08
0=
0B
0G
#27500000000
1!
b0111 $
1%
1'
b0111 *
1.
03
14
05
06
07
18
1:
1=
0?
1B
0D
1G
0I
1J
1K
#28000000000
0!
0%
0'
08
0=
0B
0G
#28500000000
1!
b1000 $
1%
1'
b1000 *
1+
0,
0-
0.
00
11
12
13
14
17
18
1:
1;
1<
1=
0@
0A
1B
0E
0F
1G
1I
0J
0K
#29000000000
0!
0%
0'
08
0=
0B
0G
#29500000000
1!
b1001 $
1%
1'
b1001 *
1.
03
04
07
18
0:
1=
1B
1G
0I
1J
1K
#30000000000
0!
0%
0'
08
0=
0B
0G
#30500000000
1!
b0000 $
1%
1'
b0000 *
0+
0.
10
13
17
18
0;
0<
1=
1B
1G
1I
0J
0K
#31000000000
0!
0%
0'
08
0=
0B
0G
#31500000000
1!
b0001 $
1%
1'
b0001 *
1.
03
16
07
18
1=
1B
1D
1G
0I
1J
1K
#32000000000
0!
0%
0'
08
0=
0B
0G
#32500000000
1!
b0010 $
1%
1'
b0010 *
1-
0.
02
13
16
17
18
1=
1B
1D
1E
1F
1G
1I
0J
0K
#33000000000
0!
0%
0'
08
0=
0B
0G
#33500000000
1!
b0011 $
1%
1'
b0011 *
1.
03
15
06
07
18
1=
1?
1B
0D
1G
0I
1J
1K
#34000000000
0!
0%
0'
08
0=
0B
0G
#34500000000
1!
b0100 $
1%
1'
b0100 *
1,
0-
0.
01
12
13
15
17
18
1=
1?
1@
1A
1B
0E
0F
1G
1I
0J
0K
#35000000000
0!
0%
0'
08
0=
0B
0G
#35500000000
1!
b0101 $
1%
1'
b0101 *
1.
03
16
07
18
1=
1B
1D
1G
0I
1J
1K
#36000000000
0!
0%
0'
08
0=
0B
0G
#36500000000
1!
b0110 $
1%
1'
b0110 *
1-
0.
02
13
16
17
18
1=
1B
1D
1E
1F
1G
1I
0J
0K
#37000000000
0!
0%
0'
08
0=
0B
0G
#37500000000
1!
b0111 $
1%
1'
b0111 *
1.
03
14
05
06
07
18
1:
1=
0?
1B
0D
1G
0I
1J
1K
#38000000000
0!
0%
0'
08
0=
0B
0G
#38500000000
1!
b1000 $
1%
1'
b1000 *
1+
0,
0-
0.
00
11
12
13
14
17
18
1:
1;
1<
1=
0@
0A
1B
0E
0F
1G
1I
0J
0K
#39000000000
0!
0%
0'
08
0=
0B
0G
#39500000000
1!
b1001 $
1%
1'
b1001 *
1.
03
04
07
18
0:
1=
1B
1G
0I
1J
1K
#40000000000
0!
0%
0'
08
0=
0B
0G
#40500000000
1!
b0000 $
1%
1'
b0000 *
0+
0.
10
13
17
18
0;
0<
1=
1B
1G
1I
0J
0K
#41000000000
0!
0%
0'
08
0=
0B
0G
#41500000000
1!
b0001 $
1%
1'
b0001 *
1.
03
16
07
18
1=
1B
1D
1G
0I
1J
1K
#42000000000
0!
0%
0'
08
0=
0B
0G
#42500000000
1!
b0010 $
1%
1'
b0010 *
1-
0.
02
13
16
17
18
1=
1B
1D
1E
1F
1G
1I
0J
0K
#43000000000
0!
0%
0'
08
0=
0B
0G
#43500000000
1!
b0011 $
1%
1'
b0011 *
1.
03
15
06
07
18
1=
1?
1B
0D
1G
0I
1J
1K
#44000000000
0!
0%
0'
08
0=
0B
0G
#44500000000
1!
b0100 $
1%
1'
b0100 *
1,
0-
0.
01
12
13
15
17
18
1=
1?
1@
1A
1B
0E
0F
1G
1I
0J
0K
#45000000000
0!
0%
0'
08
0=
0B
0G
#45500000000
1!
b0101 $
1%
1'
b0101 *
1.
03
16
07
18
1=
1B
1D
1G
0I
1J
1K
#46000000000
0!
0%
0'
08
0=
0B
0G
#46500000000
1!
b0110 $
1%
1'
b0110 *
1-
0.
02
13
16
17
18
1=
1B
1D
1E
1F
1G
1I
0J
0K
#47000000000
0!
0%
0'
08
0=
0B
0G
#47500000000
1!
b0111 $
1%
1'
b0111 *
1.
03
14
05
06
07
18
1:
1=
0?
1B
0D
1G
0I
1J
1K
#48000000000
0!
0%
0'
08
0=
0B
0G
#48500000000
1!
b1000 $
1%
1'
b1000 *
1+
0,
0-
0.
00
11
12
13
14
17
18
1:
1;
1<
1=
0@
0A
1B
0E
0F
1G
1I
0J
0K
#49000000000
0!
0%
0'
08
0=
0B
0G
#49500000000
1!
b1001 $
1%
1'
b1001 *
1.
03
04
07
18
0:
1=
1B
1G
0I
1J
1K
#50000000000
0!
0%
0'
08
0=
0B
0G
#50500000000
1!
b0000 $
1%
1'
b0000 *
0+
0.
10
13
17
18
0;
0<
1=
1B
1G
1I
0J
0K
#51000000000
0!
0%
0'
08
0=
0B
0G
#51500000000
1!
b0001 $
1%
1'
b0001 *
1.
03
16
07
18
1=
1B
1D
1G
0I
1J
1K
#52000000000
0!
0%
0'
08
0=
0B
0G
#52500000000
1!
b0010 $
1%
1'
b0010 *
1-
0.
02
13
16
17
18
1=
1B
1D
1E
1F
1G
1I
0J
0K
#53000000000
0!
0%
0'
08
0=
0B
0G
#53500000000
1!
b0011 $
1%
1'
b0011 *
1.
03
15
06
07
18
1=
1?
1B
0D
1G
0I
1J
1K
#54000000000
0!
0%
0'
08
0=
0B
0G
#54500000000
1!
b0100 $
1%
1'
b0100 *
1,
0-
0.
01
12
13
15
17
18
1=
1?
1@
1A
1B
0E
0F
1G
1I
0J
0K
#55000000000
0!
0%
0'
08
0=
0B
0G
#55500000000
1!
b0101 $
1%
1'
b0101 *
1.
03
16
07
18
1=
1B
1D
1G
0I
1J
1K
#56000000000
0!
0%
0'
08
0=
0B
0G
#56500000000
1!
b0110 $
1%
1'
b0110 *
1-
0.
02
13
16
17
18
1=
1B
1D
1E
1F
1G
1I
0J
0K
#57000000000
0!
0%
0'
08
0=
0B
0G
#57500000000
1!
b0111 $
1%
1'
b0111 *
1.
03
14
05
06
07
18
1:
1=
0?
1B
0D
1G
0I
1J
1K
#58000000000
0!
0%
0'
08
0=
0B
0G
#58500000000
1!
b1000 $
1%
1'
b1000 *
1+
0,
0-
0.
00
11
12
13
14
17
18
1:
1;
1<
1=
0@
0A
1B
0E
0F
1G
1I
0J
0K
#59000000000
0!
0%
0'
08
0=
0B
0G
#59500000000
1!
b1001 $
1%
1'
b1001 *
1.
03
04
07
18
0:
1=
1B
1G
0I
1J
1K
#60000000000
0!
0%
0'
08
0=
0B
0G
#60500000000
1!
b0000 $
1%
1'
b0000 *
0+
0.
10
13
17
18
0;
0<
1=
1B
1G
1I
0J
0K
#61000000000
0!
0%
0'
08
0=
0B
0G
#61500000000
1!
b0001 $
1%
1'
b0001 *
1.
03
16
07
18
1=
1B
1D
1G
0I
1J
1K
#62000000000
0!
0%
0'
08
0=
0B
0G
#62500000000
1!
b0010 $
1%
1'
b0010 *
1-
0.
02
13
16
17
18
1=
1B
1D
1E
1F
1G
1I
0J
0K
#63000000000
0!
0%
0'
08
0=
0B
0G
#63500000000
1!
b0011 $
1%
1'
b0011 *
1.
03
15
06
07
18
1=
1?
1B
0D
1G
0I
1J
1K
#64000000000
0!
0%
0'
08
0=
0B
0G
#64500000000
1!
b0100 $
1%
1'
b0100 *
1,
0-
0.
01
12
13
15
17
18
1=
1?
1@
1A
1B
0E
0F
1G
1I
0J
0K
#65000000000
0!
0%
0'
08
0=
0B
0G
#65500000000
1!
b0101 $
1%
1'
b0101 *
1.
03
16
07
18
1=
1B
1D
1G
0I
1J
1K
#66000000000
0!
0%
0'
08
0=
0B
0G
#66500000000
1!
b0110 $
1%
1'
b0110 *
1-
0.
02
13
16
17
18
1=
1B
1D
1E
1F
1G
1I
0J
0K
#67000000000
0!
0%
0'
08
0=
0B
0G
#67500000000
1!
b0111 $
1%
1'
b0111 *
1.
03
14
05
06
07
18
1:
1=
0?
1B
0D
1G
0I
1J
1K
#68000000000
0!
0%
0'
08
0=
0B
0G
#68500000000
1!
b1000 $
1%
1'
b1000 *
1+
0,
0-
0.
00
11
12
13
14
17
18
1:
1;
1<
1=
0@
0A
1B
0E
0F
1G
1I
0J
0K
#69000000000
0!
0%
0'
08
0=
0B
0G
#69500000000
1!
b1001 $
1%
1'
b1001 *
1.
03
04
07
18
0:
1=
1B
1G
0I
1J
1K
#70000000000
0!
0%
0'
08
0=
0B
0G
#70500000000
1!
b0000 $
1%
1'
b0000 *
0+
0.
10
13
17
18
0;
0<
1=
1B
1G
1I
0J
0K
#71000000000
0!
0%
0'
08
0=
0B
0G
#71500000000
1!
b0001 $
1%
1'
b0001 *
1.
03
16
07
18
1=
1B
1D
1G
0I
1J
1K
#72000000000
0!
0%
0'
08
0=
0B
0G
#72500000000
1!
b0010 $
1%
1'
b0010 *
1-
0.
02
13
16
17
18
1=
1B
1D
1E
1F
1G
1I
0J
0K
#73000000000
0!
0%
0'
08
0=
0B
0G
#73500000000
1!
b0011 $
1%
1'
b0011 *
1.
03
15
06
07
18
1=
1?
1B
0D
1G
0I
1J
1K
#74000000000
0!
0%
0'
08
0=
0B
0G
#74500000000
1!
b0100 $
1%
1'
b0100 *
1,
0-
0.
01
12
13
15
17
18
1=
1?
1@
1A
1B
0E
0F
1G
1I
0J
0K
#75000000000
0!
0%
0'
08
0=
0B
0G
#75500000000
1!
b0101 $
1%
1'
b0101 *
1.
03
16
07
18
1=
1B
1D
1G
0I
1J
1K
#76000000000
0!
0%
0'
08
0=
0B
0G
#76500000000
1!
b0110 $
1%
1'
b0110 *
1-
0.
02
13
16
17
18
1=
1B
1D
1E
1F
1G
1I
0J
0K
#77000000000
0!
0%
0'
08
0=
0B
0G
#77500000000
1!
b0111 $
1%
1'
b0111 *
1.
03
14
05
06
07
18
1:
1=
0?
1B
0D
1G
0I
1J
1K
#78000000000
0!
0%
0'
08
0=
0B
0G
#78500000000
1!
b1000 $
1%
1'
b1000 *
1+
0,
0-
0.
00
11
12
13
14
17
18
1:
1;
1<
1=
0@
0A
1B
0E
0F
1G
1I
0J
0K
#79000000000
0!
0%
0'
08
0=
0B
0G
#79500000000
1!
b1001 $
1%
1'
b1001 *
1.
03
04
07
18
0:
1=
1B
1G
0I
1J
1K
#80000000000
0!
0%
0'
08
0=
0B
0G
#80500000000
1!
b0000 $
1%
1'
b0000 *
0+
0.
10
13
17
18
0;
0<
1=
1B
1G
1I
0J
0K
#81000000000
0!
0%
0'
08
0=
0B
0G
#81500000000
1!
b0001 $
1%
1'
b0001 *
1.
03
16
07
18
1=
1B
1D
1G
0I
1J
1K
#82000000000
0!
0%
0'
08
0=
0B
0G
#82500000000
1!
b0010 $
1%
1'
b0010 *
1-
0.
02
13
16
17
18
1=
1B
1D
1E
1F
1G
1I
0J
0K
#83000000000
0!
0%
0'
08
0=
0B
0G
#83500000000
1!
b0011 $
1%
1'
b0011 *
1.
03
15
06
07
18
1=
1?
1B
0D
1G
0I
1J
1K
#84000000000
0!
0%
0'
08
0=
0B
0G
#84500000000
1!
b0100 $
1%
1'
b0100 *
1,
0-
0.
01
12
13
15
17
18
1=
1?
1@
1A
1B
0E
0F
1G
1I
0J
0K
#85000000000
0!
0%
0'
08
0=
0B
0G
#85500000000
1!
b0101 $
1%
1'
b0101 *
1.
03
16
07
18
1=
1B
1D
1G
0I
1J
1K
#86000000000
0!
0%
0'
08
0=
0B
0G
#86500000000
1!
b0110 $
1%
1'
b0110 *
1-
0.
02
13
16
17
18
1=
1B
1D
1E
1F
1G
1I
0J
0K
#87000000000
0!
0%
0'
08
0=
0B
0G
#87500000000
1!
b0111 $
1%
1'
b0111 *
1.
03
14
05
06
07
18
1:
1=
0?
1B
0D
1G
0I
1J
1K
#88000000000
0!
0%
0'
08
0=
0B
0G
#88500000000
1!
b1000 $
1%
1'
b1000 *
1+
0,
0-
0.
00
11
12
13
14
17
18
1:
1;
1<
1=
0@
0A
1B
0E
0F
1G
1I
0J
0K
#89000000000
0!
0%
0'
08
0=
0B
0G
#89500000000
1!
b1001 $
1%
1'
b1001 *
1.
03
04
07
18
0:
1=
1B
1G
0I
1J
1K
#90000000000
0!
0%
0'
08
0=
0B
0G
#90500000000
1!
b0000 $
1%
1'
b0000 *
0+
0.
10
13
17
18
0;
0<
1=
1B
1G
1I
0J
0K
#91000000000
0!
0%
0'
08
0=
0B
0G
#91500000000
1!
b0001 $
1%
1'
b0001 *
1.
03
16
07
18
1=
1B
1D
1G
0I
1J
1K
#92000000000
0!
0%
0'
08
0=
0B
0G
#92500000000
1!
b0010 $
1%
1'
b0010 *
1-
0.
02
13
16
17
18
1=
1B
1D
1E
1F
1G
1I
0J
0K
#93000000000
0!
0%
0'
08
0=
0B
0G
#93500000000
1!
b0011 $
1%
1'
b0011 *
1.
03
15
06
07
18
1=
1?
1B
0D
1G
0I
1J
1K
#94000000000
0!
0%
0'
08
0=
0B
0G
#94500000000
1!
b0100 $
1%
1'
b0100 *
1,
0-
0.
01
12
13
15
17
18
1=
1?
1@
1A
1B
0E
0F
1G
1I
0J
0K
#95000000000
0!
0%
0'
08
0=
0B
0G
#95500000000
1!
b0101 $
1%
1'
b0101 *
1.
03
16
07
18
1=
1B
1D
1G
0I
1J
1K
#96000000000
0!
0%
0'
08
0=
0B
0G
#96500000000
1!
b0110 $
1%
1'
b0110 *
1-
0.
02
13
16
17
18
1=
1B
1D
1E
1F
1G
1I
0J
0K
#97000000000
0!
0%
0'
08
0=
0B
0G
#97500000000
1!
b0111 $
1%
1'
b0111 *
1.
03
14
05
06
07
18
1:
1=
0?
1B
0D
1G
0I
1J
1K
#98000000000
0!
0%
0'
08
0=
0B
0G
#98500000000
1!
b1000 $
1%
1'
b1000 *
1+
0,
0-
0.
00
11
12
13
14
17
18
1:
1;
1<
1=
0@
0A
1B
0E
0F
1G
1I
0J
0K
#99000000000
0!
0%
0'
08
0=
0B
0G
#99500000000
1!
b1001 $
1%
1'
b1001 *
1.
03
04
07
18
0:
1=
1B
1G
0I
1J
1K
#100000000000
0!
0%
0'
08
0=
0B
0G
#100500000000
1!
b0000 $
1%
1'
b0000 *
0+
0.
10
13
17
18
0;
0<
1=
1B
1G
1I
0J
0K
#101000000000
0!
0%
0'
08
0=
0B
0G
#101500000000
1!
b0001 $
1%
1'
b0001 *
1.
03
16
07
18
1=
1B
1D
1G
0I
1J
1K
#102000000000
0!
1#
0%
0'
1)
0/
06
08
0=
0B
0D
0G
#102500000000
1!
b0000 $
1%
1'
b0000 *
0.
13
14
17
18
1:
1=
1B
1G
1I
0J
0K
#103000000000
0!
0%
0'
08
0=
0B
0G
#103500000000
1!
b1001 $
1%
1'
b1001 *
1+
1.
00
03
05
06
07
18
1;
1<
1=
0?
1B
0D
1G
0I
1J
1K
#104000000000
0!
0%
0'
08
0=
0B
0G
#104500000000
1!
b1000 $
1%
1'
b1000 *
0.
13
04
15
16
17
18
0:
1=
1?
1B
1D
1G
1I
0J
0K
#105000000000
0!
0%
0'
08
0=
0B
0G
#105500000000
1!
b0111 $
1%
1'
b0111 *
0+
1,
1-
1.
10
01
02
03
07
18
0;
0<
1=
1@
1A
1B
1E
1F
1G
0I
1J
1K
#106000000000
0!
0%
0'
08
0=
0B
0G
#106500000000
1!
b0110 $
1%
1'
b0110 *
0.
13
15
06
17
18
1=
1?
1B
0D
1G
1I
0J
0K
#107000000000
0!
0%
0'
08
0=
0B
0G
#107500000000
1!
b0101 $
1%
1'
b0101 *
0-
1.
12
03
07
18
1=
1B
0E
0F
1G
0I
1J
1K
#108000000000
0!
0%
0'
08
0=
0B
0G
#108500000000
1!
b0100 $
1%
1'
b0100 *
0.
13
05
16
17
18
1=
0?
1B
1D
1G
1I
0J
0K
#109000000000
0!
0%
0'
08
0=
0B
0G
#109500000000
1!
b0011 $
1%
1'
b0011 *
0,
1-
1.
11
02
03
07
18
1=
0@
0A
1B
1E
1F
1G
0I
1J
1K
#110000000000
0!
0%
0'
08
0=
0B
0G
#110500000000
1!
b0010 $
1%
1'
b0010 *
0.
13
06
17
18
1=
1B
0D
1G
1I
0J
0K
#111000000000
0!
0%
0'
08
0=
0B
0G
#111500000000
1!
b0001 $
1%
1'
b0001 *
0-
1.
12
03
07
18
1=
1B
0E
0F
1G
0I
1J
1K
#112000000000
0!
0%
0'
08
0=
0B
0G
#112500000000
1!
b0000 $
1%
1'
b0000 *
0.
13
14
17
18
1:
1=
1B
1G
1I
0J
0K
#113000000000
0!
0%
0'
08
0=
0B
0G
#113500000000
1!
b1001 $
1%
1'
b1001 *
1+
1.
00
03
05
06
07
18
1;
1<
1=
0?
1B
0D
1G
0I
1J
1K
#114000000000
0!
0%
0'
08
0=
0B
0G
#114500000000
1!
b1000 $
1%
1'
b1000 *
0.
13
04
15
16
17
18
0:
1=
1?
1B
1D
1G
1I
0J
0K
#115000000000
0!
0%
0'
08
0=
0B
0G
#115500000000
1!
b0111 $
1%
1'
b0111 *
0+
1,
1-
1.
10
01
02
03
07
18
0;
0<
1=
1@
1A
1B
1E
1F
1G
0I
1J
1K
#116000000000
0!
0%
0'
08
0=
0B
0G
#116500000000
1!
b0110 $
1%
1'
b0110 *
0.
13
15
06
17
18
1=
1?
1B
0D
1G
1I
0J
0K
#117000000000
0!
0%
0'
08
0=
0B
0G
#117500000000
1!
b0101 $
1%
1'
b0101 *
0-
1.
12
03
07
18
1=
1B
0E
0F
1G
0I
1J
1K
#118000000000
0!
0%
0'
08
0=
0B
0G
#118500000000
1!
b0100 $
1%
1'
b0100 *
0.
13
05
16
17
18
1=
0?
1B
1D
1G
1I
0J
0K
#119000000000
0!
0%
0'
08
0=
0B
0G
#119500000000
1!
b0011 $
1%
1'
b0011 *
0,
1-
1.
11
02
03
07
18
1=
0@
0A
1B
1E
1F
1G
0I
1J
1K
#120000000000
0!
0%
0'
08
0=
0B
0G
#120500000000
1!
b0010 $
1%
1'
b0010 *
0.
13
06
17
18
1=
1B
0D
1G
1I
0J
0K
#121000000000
0!
0%
0'
08
0=
0B
0G
#121500000000
1!
b0001 $
1%
1'
b0001 *
0-
1.
12
03
07
18
1=
1B
0E
0F
1G
0I
1J
1K
#122000000000
0!
0%
0'
08
0=
0B
0G
#122500000000
1!
b0000 $
1%
1'
b0000 *
0.
13
14
17
18
1:
1=
1B
1G
1I
0J
0K
#123000000000
0!
0%
0'
08
0=
0B
0G
#123500000000
1!
b1001 $
1%
1'
b1001 *
1+
1.
00
03
05
06
07
18
1;
1<
1=
0?
1B
0D
1G
0I
1J
1K
#124000000000
0!
0%
0'
08
0=
0B
0G
#124500000000
1!
b1000 $
1%
1'
b1000 *
0.
13
04
15
16
17
18
0:
1=
1?
1B
1D
1G
1I
0J
0K
#125000000000
0!
0%
0'
08
0=
0B
0G
#125500000000
1!
b0111 $
1%
1'
b0111 *
0+
1,
1-
1.
10
01
02
03
07
18
0;
0<
1=
1@
1A
1B
1E
1F
1G
0I
1J
1K
#126000000000
0!
0%
0'
08
0=
0B
0G
#126500000000
1!
b0110 $
1%
1'
b0110 *
0.
13
15
06
17
18
1=
1?
1B
0D
1G
1I
0J
0K
#127000000000
0!
0%
0'
08
0=
0B
0G
#127500000000
1!
b0101 $
1%
1'
b0101 *
0-
1.
12
03
07
18
1=
1B
0E
0F
1G
0I
1J
1K
#128000000000
0!
0%
0'
08
0=
0B
0G
#128500000000
1!
b0100 $
1%
1'
b0100 *
0.
13
05
16
17
18
1=
0?
1B
1D
1G
1I
0J
0K
#129000000000
0!
0%
0'
08
0=
0B
0G
#129500000000
1!
b0011 $
1%
1'
b0011 *
0,
1-
1.
11
02
03
07
18
1=
0@
0A
1B
1E
1F
1G
0I
1J
1K
#130000000000
0!
0%
0'
08
0=
0B
0G
#130500000000
1!
b0010 $
1%
1'
b0010 *
0.
13
06
17
18
1=
1B
0D
1G
1I
0J
0K
#131000000000
0!
0%
0'
08
0=
0B
0G
#131500000000
1!
b0001 $
1%
1'
b0001 *
0-
1.
12
03
07
18
1=
1B
0E
0F
1G
0I
1J
1K
#132000000000
0!
0%
0'
08
0=
0B
0G
