flipflops and ripple counter/seq_circuit.vhdl


library IEEE;
use IEEE.std_logic_1164.all;
entity seq_circuit is
  port (
    x,reset:in std_logic;
    clk_1:in std_logic;
    z:out std_logic
  ) ;
end seq_circuit;

architecture work of seq_circuit is
component D_flip_flop is
    port(
    	D:in std_logic;
        clk:in std_logic;
        Q:out std_logic);
end component;
    signal q1 :std_logic:='0';
    signal q2 :std_logic:='0';
    signal d1,d2 :std_logic;

begin
d1 <= (x xor q1) and (not reset);
d2 <= (x xnor q2) and (not reset);
F_1:D_flip_flop  port map(d1,clk_1,q1);
F_2:D_flip_flop  port map(d2,clk_1,q2);

z <= (not q1) or (not q2);

end work ; -- work
----------------------------------------------------------------
library IEEE;
use IEEE.std_logic_1164.all;

entity D_flip_flop is
	port(
    	D:in std_logic;
        clk:in std_logic;
        Q:out std_logic);
end D_flip_flop;

architecture flipflop of D_flip_flop is
    begin
        process (clk) is
            begin
                if rising_edge(clk) then
                    Q <= D;
                end if;
        end process;
end architecture;
--------------------------------------------------------------

---------------------------------------------------------------------

flipflops and ripple counter/seq_circuit_tb.vhdl
library ieee;
use ieee.std_logic_1164.all;

entity tb_seq_circuit is
end tb_seq_circuit;

architecture tb of tb_seq_circuit is

    component seq_circuit
        port (x     : in std_logic;
        	  reset : in std_logic;
              clk_1 : in std_logic;
              z     : out std_logic);
    end component;

    signal x     : std_logic;
    signal reset : std_logic;
    signal clk_1 : std_logic;
    signal z     : std_logic;

    constant TbPeriod : time := 1000 ns; -- EDIT Put right period here
    signal TbClock : std_logic := '0';
    signal TbSimEnded : std_logic := '0';

begin

    dut : seq_circuit
    port map (x     => x,
    		  reset => reset,
              clk_1 => clk_1,
              z     => z);

    -- Clock generation
    TbClock <= not TbClock after TbPeriod/2 when TbSimEnded /= '1' else '0';

    -- EDIT: Check that clk_1 is really your main clock signal
    clk_1 <= TbClock;

    stimuli : process
    begin
        -- EDIT Adapt initialization as needed
        reset <= '1';
        wait for TbPeriod;
        x <= '0';
        reset <='0';
        wait for TbPeriod;
        x <= '1';
        wait for TbPeriod;
        x <= '0';
        wait for TbPeriod;
        x <= '1';
        wait for TbPeriod;
        x <= '1';
        wait for TbPeriod;
        x <= '0';
        wait for TbPeriod;
        x <= '1';
        wait for TbPeriod;
        x <= '0';
        wait for TbPeriod;
        x <= '1';
        wait for TbPeriod;
        x <= '0';
        reset <='0';
        wait for TbPeriod;
        x <= '1';
        wait for TbPeriod;
        
        reset <= '1';
        wait for TbPeriod;
        x <= '1';
        reset <='0';
        wait for TbPeriod;
        x <= '0';
        wait for TbPeriod;
        x <= '1';
        wait for TbPeriod;
        x <= '1';
        wait for TbPeriod;
        x <= '0';
        wait for TbPeriod;
        x <= '1';
        wait for TbPeriod;
        x <= '0';
        wait for TbPeriod;
        x <= '1';
        wait for TbPeriod;
        x <= '0';
        wait for TbPeriod;
        x <= '1';
        reset <='0';
        wait for TbPeriod;
        x <= '0';
        wait for TbPeriod;
        
        reset <= '1';
        wait for TbPeriod;
        x <= '1';
        reset <='0';
        wait for TbPeriod;
        x <= '0';
        wait for TbPeriod;
        x <= '1';
        wait for TbPeriod;
        x <= '1';
        wait for TbPeriod;
        x <= '1';
        wait for TbPeriod;
        x <= '0';
        wait for TbPeriod;
        x <= '1';
        wait for TbPeriod;
        x <= '0';
        wait for TbPeriod;
        x <= '0';
        wait for TbPeriod;
        x <= '1';
        reset <='0';
        wait for TbPeriod;
        x <= '0';
        wait for TbPeriod;
        

        -- Stop the clock and hence terminate the simulation
        TbSimEnded <= '1';
        wait;
    end process;

end tb;

flipflops and ripple counter/tb_seq_circuit.vcd
$date
  Sun Apr 10 23:05:26 2022
$end
$version
  GHDL v0
$end
$timescale
  1 fs
$end
$scope module standard $end
$upscope $end
$scope module std_logic_1164 $end
$upscope $end
$scope module tb_seq_circuit $end
$var reg 1 ! x $end
$var reg 1 " reset $end
$var reg 1 # clk_1 $end
$var reg 1 $ z $end
$var reg 1 % tbclock $end
$var reg 1 & tbsimended $end
$scope module dut $end
$var reg 1 ' x $end
$var reg 1 ( reset $end
$var reg 1 ) clk_1 $end
$var reg 1 * z $end
$var reg 1 + q1 $end
$var reg 1 , q2 $end
$var reg 1 - d1 $end
$var reg 1 . d2 $end
$scope module f_1 $end
$var reg 1 / d $end
$var reg 1 0 clk $end
$var reg 1 1 q $end
$upscope $end
$scope module f_2 $end
$var reg 1 2 d $end
$var reg 1 3 clk $end
$var reg 1 4 q $end
$upscope $end
$upscope $end
$upscope $end
$enddefinitions $end
#0
U!
1"
0#
U$
0%
0&
U'
1(
0)
U*
U+
U,
0-
0.
0/
00
U1
02
03
U4
#500000000
1#
1$
1%
1)
1*
0+
0,
10
01
13
04
#1000000000
0!
0"
0#
0%
0'
0(
0)
1.
00
12
03
#1500000000
1#
1%
1)
1,
0.
10
02
13
14
#2000000000
1!
0#
0%
1'
0)
1-
1.
1/
00
12
03
#2500000000
1#
0$
1%
1)
0*
1+
0-
0/
10
11
13
#3000000000
0!
0#
0%
0'
0)
1-
0.
1/
00
02
03
#3500000000
1#
1$
1%
1)
1*
0,
1.
10
12
13
04
#4000000000
1!
0#
0%
1'
0)
0-
0.
0/
00
02
03
#4500000000
1#
1%
1)
0+
1-
1/
10
01
13
#5000000000
0#
0%
0)
00
03
#5500000000
1#
1%
1)
1+
0-
0/
10
11
13
#6000000000
0!
0#
0%
0'
0)
1-
1.
1/
00
12
03
#6500000000
1#
0$
1%
1)
0*
1,
0.
10
02
13
14
#7000000000
1!
0#
0%
1'
0)
0-
1.
0/
00
12
03
#7500000000
1#
1$
1%
1)
1*
0+
1-
1/
10
01
13
#8000000000
0!
0#
0%
0'
0)
0-
0.
0/
00
02
03
#8500000000
1#
1%
1)
0,
1.
10
12
13
04
#9000000000
1!
0#
0%
1'
0)
1-
0.
1/
00
02
03
#9500000000
1#
1%
1)
1+
0-
0/
10
11
13
#10000000000
0!
0#
0%
0'
0)
1-
1.
1/
00
12
03
#10500000000
1#
0$
1%
1)
0*
1,
0.
10
02
13
14
#11000000000
1!
0#
0%
1'
0)
0-
1.
0/
00
12
03
#11500000000
1#
1$
1%
1)
1*
0+
1-
1/
10
01
13
#12000000000
1"
0#
0%
1(
0)
0-
0.
0/
00
02
03
#12500000000
1#
1%
1)
0,
10
13
04
#13000000000
0"
0#
0%
0(
0)
1-
1/
00
03
#13500000000
1#
1%
1)
1+
0-
0/
10
11
13
#14000000000
0!
0#
0%
0'
0)
1-
1.
1/
00
12
03
#14500000000
1#
0$
1%
1)
0*
1,
0.
10
02
13
14
#15000000000
1!
0#
0%
1'
0)
0-
1.
0/
00
12
03
#15500000000
1#
1$
1%
1)
1*
0+
1-
1/
10
01
13
#16000000000
0#
0%
0)
00
03
#16500000000
1#
0$
1%
1)
0*
1+
0-
0/
10
11
13
#17000000000
0!
0#
0%
0'
0)
1-
0.
1/
00
02
03
#17500000000
1#
1$
1%
1)
1*
0,
1.
10
12
13
04
#18000000000
1!
0#
0%
1'
0)
0-
0.
0/
00
02
03
#18500000000
1#
1%
1)
0+
1-
1/
10
01
13
#19000000000
0!
0#
0%
0'
0)
0-
1.
0/
00
12
03
#19500000000
1#
1%
1)
1,
0.
10
02
13
14
#20000000000
1!
0#
0%
1'
0)
1-
1.
1/
00
12
03
#20500000000
1#
0$
1%
1)
0*
1+
0-
0/
10
11
13
#21000000000
0!
0#
0%
0'
0)
1-
0.
1/
00
02
03
#21500000000
1#
1$
1%
1)
1*
0,
1.
10
12
13
04
#22000000000
1!
0#
0%
1'
0)
0-
0.
0/
00
02
03
#22500000000
1#
1%
1)
0+
1-
1/
10
01
13
#23000000000
0!
0#
0%
0'
0)
0-
1.
0/
00
12
03
#23500000000
1#
1%
1)
1,
0.
10
02
13
14
#24000000000
1"
0#
0%
1(
0)
00
03
#24500000000
1#
1%
1)
0,
10
13
04
#25000000000
1!
0"
0#
0%
1'
0(
0)
1-
1/
00
03
#25500000000
1#
1%
1)
1+
0-
0/
10
11
13
#26000000000
0!
0#
0%
0'
0)
1-
1.
1/
00
12
03
#26500000000
1#
0$
1%
1)
0*
1,
0.
10
02
13
14
#27000000000
1!
0#
0%
1'
0)
0-
1.
0/
00
12
03
#27500000000
1#
1$
1%
1)
1*
0+
1-
1/
10
01
13
#28000000000
0#
0%
0)
00
03
#28500000000
1#
0$
1%
1)
0*
1+
0-
0/
10
11
13
#29000000000
0#
0%
0)
00
03
#29500000000
1#
1$
1%
1)
1*
0+
1-
1/
10
01
13
#30000000000
0!
0#
0%
0'
0)
0-
0.
0/
00
02
03
#30500000000
1#
1%
1)
0,
1.
10
12
13
04
#31000000000
1!
0#
0%
1'
0)
1-
0.
1/
00
02
03
#31500000000
1#
1%
1)
1+
0-
0/
10
11
13
#32000000000
0!
0#
0%
0'
0)
1-
1.
1/
00
12
03
#32500000000
1#
0$
1%
1)
0*
1,
0.
10
02
13
14
#33000000000
0#
0%
0)
00
03
#33500000000
1#
1$
1%
1)
1*
0,
1.
10
12
13
04
#34000000000
1!
0#
0%
1'
0)
0-
0.
0/
00
02
03
#34500000000
1#
1%
1)
0+
1-
1/
10
01
13
#35000000000
0!
0#
0%
0'
0)
0-
1.
0/
00
12
03
#35500000000
1#
1%
1)
1,
0.
10
02
13
14
#36000000000
0#
0%
1&
0)
00
03
